werkzeug_raw.py
Werkzeug_Raw-0.0.2.dist-info/METADATA
Werkzeug_Raw-0.0.2.dist-info/RECORD
Werkzeug_Raw-0.0.2.dist-info/WHEEL
Werkzeug_Raw-0.0.2.dist-info/top_level.txt
