Metadata-Version: 1.1
Name: Werkzeug-Raw
Version: 0.0.2
Summary: Werkzeug meets Raw HTTP
Home-page: http://pythonhosted.org/Werkzeug-Raw/
Author: Nathan Cahill
Author-email: nathan@nathancahill.com
License: MIT
Keywords: werkzeug flask http
Platform: UNKNOWN
Classifier: Development Status :: 4 - Beta
Classifier: Intended Audience :: Developers
Classifier: Topic :: Software Development :: Libraries :: Python Modules
Classifier: Operating System :: OS Independent
Classifier: Programming Language :: Python :: 2.7
Classifier: Programming Language :: Python :: 3.4
Classifier: Programming Language :: Python :: 3.5
Classifier: Programming Language :: Python :: 3.6
